document_to_podcast/__init__.py
document_to_podcast/cli.py
document_to_podcast/config.py
document_to_podcast/utils.py
document_to_podcast/inference/__init__.py
document_to_podcast/inference/model_loaders.py
document_to_podcast/inference/text_to_speech.py
document_to_podcast/inference/text_to_text.py
document_to_podcast/inference/kokoro/__init__.py
document_to_podcast/inference/kokoro/infer.py
document_to_podcast/inference/kokoro/istftnet.py
document_to_podcast/inference/kokoro/models.py
document_to_podcast/inference/kokoro/plbert.py
document_to_podcast/preprocessing/__init__.py
document_to_podcast/preprocessing/data_cleaners.py
document_to_podcast/preprocessing/data_loaders.py
document_to_podcast-1.4.2.dist-info/LICENSE
document_to_podcast-1.4.2.dist-info/METADATA
document_to_podcast-1.4.2.dist-info/WHEEL
document_to_podcast-1.4.2.dist-info/entry_points.txt
document_to_podcast-1.4.2.dist-info/top_level.txt
document_to_podcast-1.4.2.dist-info/RECORD
