Metadata-Version: 2.2
Name: document-to-podcast
Version: 1.4.2
License: Apache-2.0
Project-URL: Documentation, https://mozilla-ai.github.io/document-to-podcast/
Project-URL: Issues, https://github.com/mozilla-ai/document-to-podcast/issues
Project-URL: Source, https://github.com/mozilla-ai/document-to-podcast
Requires-Python: <3.13,>=3.10
License-File: LICENSE
Requires-Dist: beautifulsoup4
Requires-Dist: fire
Requires-Dist: huggingface-hub
Requires-Dist: llama-cpp-python
Requires-Dist: loguru
Requires-Dist: outetts<0.3
Requires-Dist: pydantic
Requires-Dist: PyPDF2[crypto]
Requires-Dist: python-docx
Requires-Dist: streamlit
Provides-Extra: docs
Requires-Dist: mkdocs; extra == "docs"
Requires-Dist: mkdocs-material; extra == "docs"
Requires-Dist: mkdocstrings-python; extra == "docs"
Provides-Extra: tests
Requires-Dist: pytest<9,>=8; extra == "tests"
Requires-Dist: pytest-sugar>=0.9.6; extra == "tests"
Requires-Dist: pytest-mock>=3.14.0; extra == "tests"
